Metadata-Version: 2.4
Name: databricks-mcp-server
Version: 0.4.4
Summary: A Model Context Protocol (MCP) server for Databricks
Author-email: Olivier Debeuf De Rijcker <olivier@markov.bot>
License: MIT
Keywords: ai,cursor,databricks,llm,mcp,model-context-protocol
Classifier: Development Status :: 4 - Beta
Classifier: Intended Audience :: Developers
Classifier: License :: OSI Approved :: MIT License
Classifier: Operating System :: OS Independent
Classifier: Programming Language :: Python :: 3
Classifier: Programming Language :: Python :: 3.10
Classifier: Programming Language :: Python :: 3.11
Classifier: Programming Language :: Python :: 3.12
Classifier: Topic :: Internet :: WWW/HTTP :: HTTP Servers
Classifier: Topic :: Software Development :: Libraries :: Python Modules
Requires-Python: >=3.10
Requires-Dist: databricks-sdk
Requires-Dist: httpx
Requires-Dist: mcp[cli]>=1.2.0
Provides-Extra: cli
Requires-Dist: click; extra == 'cli'
Provides-Extra: dev
Requires-Dist: anyio; extra == 'dev'
Requires-Dist: black; extra == 'dev'
Requires-Dist: fastapi; extra == 'dev'
Requires-Dist: pylint; extra == 'dev'
Requires-Dist: pytest; extra == 'dev'
Requires-Dist: pytest-asyncio; extra == 'dev'
